{
    "$schema": "http://json-schema.org/draft-04/schema#",
    "type": "object",
    "properties": {
        "message": {
            "type": "string"
        },
        "params": {
            "type": "object",
            "properties": {
                "projectId": {
                    "type": "integer"
                },
                "branchId": {
                    "type": "integer"
                },
                "sourceId": {
                    "type": "string"
                },
                "streamId": {
                    "type": "string"
                },
                "sourceName": {
                    "type": "string"
                },
                "error": {
                    "type": "string"
                }
            },
            "required": [
                "projectId",
                "branchId",
                "sourceId",
                "streamId",
                "sourceName"
            ]
        },
        "results": {
            "type": "object",
            "properties": {
                "projectId": {
                    "type": "integer"
                },
                "branchId": {
                    "type": "integer"
                },
                "sourceId": {
                    "type": "string"
                },
                "streamId": {
                    "type": "string"
                },
                "sourceName": {
                    "type": "string"
                },
                "error": {
                    "type": "string"
                }
            },
            "required": [
                "projectId",
                "branchId",
                "sourceId",
                "streamId",
                "sourceName"
            ]
        }
    },
    "required": [
        "message",
        "params",
        "results"
    ]
}
